Metadata-Version: 2.1
Name: revengine
Version: 0.0.1
Summary: RevEngine
Home-page: https://github.com/primal-coder/Revengine
Author: James Evans
Author-email: joesaysahoy@gmail.com
License-File: LICENSE
